aniclustermap/__init__.py
aniclustermap/__main__.py
aniclustermap/cluster.py
aniclustermap/const.py
aniclustermap/logger.py
aniclustermap/main.py
aniclustermap/plot.py
aniclustermap/tree.py
aniclustermap/utils.py
aniclustermap/ani/__init__.py
aniclustermap/ani/matrix.py
aniclustermap/ani/tools.py
aniclustermap/bin/Linux/fastANI
aniclustermap/bin/Linux/skani
aniclustermap/scripts/__init__.py
aniclustermap/scripts/aniclustermap.py
aniclustermap-2.0.1.dist-info/METADATA
aniclustermap-2.0.1.dist-info/WHEEL
aniclustermap-2.0.1.dist-info/entry_points.txt
aniclustermap-2.0.1.dist-info/licenses/LICENSE
aniclustermap-2.0.1.dist-info/RECORD
