Metadata-Version: 2.3
Name: aniclustermap
Version: 2.0.1
Summary: A tool for drawing ANI clustermap between all-vs-all microbial genomes
Project-URL: repository, https://github.com/moshi4/ANIclustermap/
Author: moshi4
License: MIT
Keywords: bioinformatics,clustermap,genomics,phylogenetics,visualization
Classifier: Intended Audience :: Science/Research
Classifier: Topic :: Scientific/Engineering :: Bio-Informatics
Requires-Python: >=3.9
Requires-Dist: pandas>=1.4.1
Requires-Dist: scipy>=1.9.0
Requires-Dist: seaborn>=0.11.2
Requires-Dist: typer>=0.15.2
